sysflow/__init__.py
sysflow/formatter.py
sysflow/graphlet.py
sysflow/objtypes.py
sysflow/openflags.py
sysflow/opflags.py
sysflow/reader.py
sysflow/sfql.py
sysflow/utils.py
sysflow/grammar/__init__.py
sysflow/grammar/sfqlLexer.py
sysflow/grammar/sfqlListener.py
sysflow/grammar/sfqlParser.py
sysflow_tools-0.6.1.data/scripts/sysprint
sysflow_tools-0.6.1.dist-info/METADATA
sysflow_tools-0.6.1.dist-info/WHEEL
sysflow_tools-0.6.1.dist-info/top_level.txt
sysflow_tools-0.6.1.dist-info/RECORD
