Metadata-Version: 2.1
Name: sysflow-tools
Version: 0.6.1
Summary: SysFlow APIs and utilities
Home-page: https://github.com/sysflow-telemetry
License: Apache 2.0 License
Project-URL: Documentation, https://sysflow.readthedocs.io/
Keywords: system telemetry,cloud-native security,runtime observability
Classifier: Topic :: Security
Classifier: Operating System :: OS Independent
Classifier: License :: OSI Approved :: Apache Software License
Classifier: Programming Language :: Python :: 3
Classifier: Programming Language :: Python :: 3 :: Only
Requires-Python: >=3.7
Requires-Dist: tabulate >=0.8.9
Requires-Dist: minio >=7.0.3
Requires-Dist: antlr4-python3-runtime ==4.9.2
Requires-Dist: dotty-dict >=1.3.0
Requires-Dist: pandas >=1.3.0
Requires-Dist: frozendict >=2.0.3
Requires-Dist: fastavro >=1.7.0
Requires-Dist: mitreattack-python >=1.5.7
Requires-Dist: plotly >=5.5.0
Requires-Dist: seaborn >=0.11.1
Requires-Dist: graphviz >=0.17
Requires-Dist: matplotlib >=3.4.3
Requires-Dist: importlib.metadata >=4.12.0
